AUTHORS.rst
CONTRIBUTING.rst
HISTORY.rst
LICENSE
MANIFEST.in
README.rst
setup.cfg
setup.py
ansible_lint_to_junit_xml.egg-info/PKG-INFO
ansible_lint_to_junit_xml.egg-info/SOURCES.txt
ansible_lint_to_junit_xml.egg-info/dependency_links.txt
ansible_lint_to_junit_xml.egg-info/entry_points.txt
ansible_lint_to_junit_xml.egg-info/not-zip-safe
ansible_lint_to_junit_xml.egg-info/top_level.txt
ansiblelinttojunitxml/__init__.py
ansiblelinttojunitxml/ansiblelinttojunitxml.py
test/test_ansible-lint-to-junit-xml.py