Metadata-Version: 1.1
Name: ansible-lint-to-junit-xml
Version: 0.1.0
Summary: Convert ansible-lint outputs to a jUnit valid xml tests result file
Home-page: https://github.com/andreferreirav2/ansible-lint-to-junit-xml
Author: Andre Ferreira
Author-email: andre.ferreira.v2@gmail.com
License: MIT
Keywords: ansible,lint,junit,report
Platform: UNKNOWN
Classifier: Development Status :: 2 - Pre-Alpha
Classifier: Intended Audience :: Developers
Classifier: License :: OSI Approved :: MIT License
Classifier: Natural Language :: English
Classifier: Programming Language :: Python :: 2
Classifier: Programming Language :: Python :: 2.6
Classifier: Programming Language :: Python :: 2.7
Classifier: Programming Language :: Python :: 3
Classifier: Programming Language :: Python :: 3.3
Classifier: Programming Language :: Python :: Implementation :: PyPy
